ida_plugin/__init__.py
ida_plugin-0.0.0.dist-info/METADATA
ida_plugin-0.0.0.dist-info/WHEEL
ida_plugin-0.0.0.dist-info/top_level.txt
ida_plugin-0.0.0.dist-info/RECORD
