Metadata-Version: 2.4
Name: ida-plugin
Version: 0.0.0
Summary: Coming soon
Requires-Python: >=3.13
